nque/__init__.py
nque/base.py
nque/exceptions.py
nque/fifo_basic_lmdb.py
nque/fifo_multi_lmdb.py
nque-1.0.2.dist-info/licenses/LICENSE
nque-1.0.2.dist-info/METADATA
nque-1.0.2.dist-info/WHEEL
nque-1.0.2.dist-info/top_level.txt
nque-1.0.2.dist-info/RECORD
