Metadata-Version: 2.4
Name: nque
Version: 1.0.2
Summary: High-performance persistent FIFO queues with LMDB backend supporting both single-queue and multi-queue broadcast patterns.
Author-email: Artur Khakimau <arthur78@gmail.com>
License-Expression: MIT
Project-URL: Homepage, https://github.com/arthur78/nque
Project-URL: Repository, https://github.com/arthur78/nque
Classifier: Development Status :: 5 - Production/Stable
Classifier: Intended Audience :: Developers
Classifier: Operating System :: OS Independent
Classifier: Programming Language :: Python :: 3.10
Classifier: Programming Language :: Python :: 3.11
Classifier: Programming Language :: Python :: 3.12
Classifier: Programming Language :: Python :: 3.13
Classifier: Topic :: Software Development :: Libraries :: Python Modules
Classifier: Topic :: Utilities
Classifier: Typing :: Typed
Requires-Python: >=3.10
License-File: LICENSE
Requires-Dist: lmdb>=1.5.1
Dynamic: license-file
